resources/bitmap/indentguide.xbm
resources/bitmap/line.xbm
resources/bitmap/stipple.xbm
resources/fonts/codicon.ttf
resources/fonts/LICENSE-CODE-codicon
resources/fonts/LICENSE-codicon
resources/fonts/LICENSE-materialsymbols
resources/fonts/MaterialSymbols.ttf
resources/linux/icon.ico
resources/linux/icon.png
resources/linux/logo.png
resources/logo.png
resources/win32/icon.ico
resources/win32/icon.png
resources/win32/logo.ico
biscuit/__init__.py
biscuit/__main__.py
biscuit/api/__init__.py
biscuit/api/assistant.py
biscuit/api/base.py
biscuit/api/commands.py
biscuit/api/editors.py
biscuit/api/endpoint.py
biscuit/api/logger.py
biscuit/api/notifications.py
biscuit/api/README.md
biscuit/api/releases.py
biscuit/api/theme.py
biscuit/api/views.py
biscuit/app.py
biscuit/binder.py
biscuit/cli/__init__.py
biscuit/cli/cli.py
biscuit/cli/editor.py
biscuit/cli/extensions.py
biscuit/cli/git.py
biscuit/cli/README.md
biscuit/commands.py
biscuit/common/__init__.py
biscuit/common/actionset.py
biscuit/common/ai/__init__.py
biscuit/common/ai/agent.py
biscuit/common/ai/examples.py
biscuit/common/ai/langgraph_agent.py
biscuit/common/ai/modes.py
biscuit/common/ai/state.py
biscuit/common/ai/tools.py
biscuit/common/chat/__init__.py
biscuit/common/chat/gemini.py
biscuit/common/chat/model.py
biscuit/common/classdrill.py
biscuit/common/fixedstack.py
biscuit/common/games/__init__.py
biscuit/common/games/game.py
biscuit/common/games/gamebase.py
biscuit/common/games/gameoflife.py
biscuit/common/games/minesweeper.py
biscuit/common/games/pong.py
biscuit/common/games/ttt.py
biscuit/common/games/whoops.py
biscuit/common/helpers.py
biscuit/common/icons.py
biscuit/common/io.py
biscuit/common/menu/__init__.py
biscuit/common/menu/checkable.py
biscuit/common/menu/command.py
biscuit/common/menu/dropdown.py
biscuit/common/menu/menu.py
biscuit/common/menu/separator.py
biscuit/common/menu/submenu.py
biscuit/common/minclosestdict.py
biscuit/common/notifications/__init__.py
biscuit_editor-3.3.0.dist-info/entry_points.txt
biscuit_editor-3.3.0.dist-info/LICENSE.md
biscuit_editor-3.3.0.dist-info/METADATA
biscuit_editor-3.3.0.dist-info/WHEEL
biscuit_editor-3.3.0.dist-info/RECORD
