Metadata-Version: 2.1
Name: biscuit-editor
Version: 3.3.0
Summary: A lightweight, fast, and extensible code editor with a growing community
License: MIT
Author: Billy
Author-email: billydevbusiness@gmail.com
Requires-Python: >=3.10,<4.0
Classifier: License :: OSI Approved :: MIT License
Classifier: Programming Language :: Python :: 3
Classifier: Programming Language :: Python :: 3.10
Classifier: Programming Language :: Python :: 3.11
Classifier: Programming Language :: Python :: 3.12
Requires-Dist: chardet (>=5.2.0,<6.0.0)
Requires-Dist: click (>=8.1.8,<9.0.0)
Requires-Dist: editorconfig (>=0.17.0,<0.18.0)
Requires-Dist: filetype (>=1.2.0,<2.0.0)
Requires-Dist: gitpython (>=3.1.44,<4.0.0)
Requires-Dist: google-generativeai (>=0.8.4,<0.9.0)
Requires-Dist: hintedtext (>=0.6.0,<0.7.0)
Requires-Dist: langchain (>=0.3.0,<0.4.0)
Requires-Dist: langchain-community (>=0.3.0,<0.4.0)
Requires-Dist: langchain-core (>=0.3.0,<0.4.0)
Requires-Dist: langchain-google-genai (>=2.0.0,<3.0.0)
Requires-Dist: mistune (>=3.1.2,<4.0.0)
Requires-Dist: pillow (>=11.1.0,<12.0.0)
Requires-Dist: psutil (>=7.0.0,<8.0.0)
Requires-Dist: ptyprocess (>=0.7.0,<0.8.0) ; sys_platform == "linux"
Requires-Dist: pygments (>=2.19.1,<3.0.0)
Requires-Dist: pyperclip (>=1.9.0,<2.0.0)
Requires-Dist: python-tkdnd (>=0.2.1,<0.3.0)
Requires-Dist: pywinpty (>=2.0.15,<3.0.0) ; sys_platform == "win32"
Requires-Dist: requests (>=2.32.3,<3.0.0)
Requires-Dist: sortedcontainers (>=2.4.0,<3.0.0)
Requires-Dist: sv-ttk (>=2.6.0,<3.0.0)
Requires-Dist: tarts (>=0.20.1,<0.21.0)
Requires-Dist: tkextrafont (>=0.6.3,<0.7.0) ; sys_platform == "win32"
Requires-Dist: tkinterweb (>=4.2.0,<5.0.0)
Requires-Dist: toml (>=0.10.2,<0.11.0)
Requires-Dist: watchdog (>=6.0.0,<7.0.0)
